manuelharofulgencio/__init__.py
manuelharofulgencio/opengate_client.py
manuelharofulgencio/ai_models/__init__.py
manuelharofulgencio/ai_models/ai_models.py
manuelharofulgencio/ai_pipelines/__init__.py
manuelharofulgencio/ai_pipelines/ai_pipelines.py
manuelharofulgencio/ai_transformers/__init__.py
manuelharofulgencio/ai_transformers/ai_transformers.py
manuelharofulgencio/datapoints/__init__.py
manuelharofulgencio/datapoints/datapoints.py
manuelharofulgencio/datasets/__init__.py
manuelharofulgencio/datasets/datasets.py
manuelharofulgencio/entities/__init__.py
manuelharofulgencio/entities/entities.py
manuelharofulgencio/rules/__init__.py
manuelharofulgencio/rules/rules.py
manuelharofulgencio/test/__init__.py
manuelharofulgencio/test/ownworld.py
manuelharofulgencio/test/test_steps_cucumber.py
manuelharofulgencio/timeseries/__init__.py
manuelharofulgencio/timeseries/timeseries.py
manuelharofulgencio-1.0.1.dist-info/METADATA
manuelharofulgencio-1.0.1.dist-info/WHEEL
manuelharofulgencio-1.0.1.dist-info/top_level.txt
manuelharofulgencio-1.0.1.dist-info/RECORD
